django_label_templates-1.0.3.dist-info/METADATA
django_label_templates-1.0.3.dist-info/RECORD
django_label_templates-1.0.3.dist-info/WHEEL
django_label_templates-1.0.3.dist-info/top_level.txt
label_templates/__init__.py
label_templates/loaders.py
label_templates/sites.py
tests/__init__.py
tests/manage.py
tests/settings.py
tests/urls.py
tests/app/__init__.py
tests/tests/__init__.py
tests/tests/test_loaders.py
