Metadata-Version: 2.1
Name: django-label-templates
Version: 1.0.3
Summary: Load templates from site labels if available
Home-page: https://github.com/maykinmedia/django-label-templates
Author: Maykin Media, Sergei Maertens
Author-email: sergei@maykinmedia.nl
License: MIT
Platform: UNKNOWN
Classifier: Development Status :: 5 - Production/Stable
Classifier: Operating System :: OS Independent
Classifier: License :: OSI Approved :: MIT License
Classifier: Intended Audience :: Developers
Classifier: Framework :: Django
Classifier: Framework :: Django :: 1.8
Classifier: Framework :: Django :: 1.9
Classifier: Programming Language :: Python :: 2.7
Classifier: Programming Language :: Python :: 3.3
Classifier: Programming Language :: Python :: 3.4
Classifier: Programming Language :: Python :: 3.5
Classifier: Programming Language :: Python :: Implementation :: PyPy
Requires-Dist: Django (>=1.8)
Requires-Dist: django-choices
